{"target": -2799.442930000001, "params": {"spark.default.parallelism": 236.12336749045244, "spark.executor.cores": 1.8690974896313952, "spark.executor.instances": 7.671951170240832, "spark.executor.memory": 3.583488181056161, "spark.executor.memoryOverhead": 553.2866110529108, "spark.memory.fraction": 0.5464654450798986, "spark.memory.storageFraction": 0.7870260732997525, "spark.reducer.maxBlocksInFlightPerAddress": 1452468521.931183, "spark.reducer.maxSizeInFlight": 41.87728145171432, "spark.shuffle.file.buffer": 32.74684466455094}, "datetime": {"datetime": "2022-02-26 22:02:36", "elapsed": 0.0, "delta": 0.0}}
{"target": -2800.281400000001, "params": {"spark.default.parallelism": 446.0637168084804, "spark.executor.cores": 3.222443662302399, "spark.executor.instances": 5.820191821383686, "spark.executor.memory": 5.468929978233479, "spark.executor.memoryOverhead": 801.6056466691799, "spark.memory.fraction": 0.8099670967617874, "spark.memory.storageFraction": 0.7663841092222615, "spark.reducer.maxBlocksInFlightPerAddress": 1829209181.9953232, "spark.reducer.maxSizeInFlight": 34.073079437163244, "spark.shuffle.file.buffer": 47.572296853686204}, "datetime": {"datetime": "2022-02-26 22:02:36", "elapsed": 0.195479, "delta": 0.195479}}
{"target": -2803.324520000001, "params": {"spark.default.parallelism": 399.1938625773528, "spark.executor.cores": 2.402935841838682, "spark.executor.instances": 4.283378039480433, "spark.executor.memory": 6.210053322690313, "spark.executor.memoryOverhead": 432.325812010409, "spark.memory.fraction": 0.7396833495363009, "spark.memory.storageFraction": 0.6065353500040451, "spark.reducer.maxBlocksInFlightPerAddress": 1157261418.9941275, "spark.reducer.maxSizeInFlight": 69.21122492165263, "spark.shuffle.file.buffer": 18.824591172840297}, "datetime": {"datetime": "2022-02-26 22:02:37", "elapsed": 0.437833, "delta": 0.242354}}
