{"target": -2796.766810000001, "params": {"spark.default.parallelism": 487.4477473393995, "spark.executor.cores": 2.898203738856469, "spark.executor.instances": 5.826073915815975, "spark.executor.memory": 4.856155069321345, "spark.executor.memoryOverhead": 800.0903111729144, "spark.memory.fraction": 0.8995231729933673, "spark.memory.storageFraction": 0.8185505614556003, "spark.reducer.maxBlocksInFlightPerAddress": 1298246994.7161071, "spark.reducer.maxSizeInFlight": 58.09011524605587, "spark.shuffle.file.buffer": 42.95084061104467}, "datetime": {"datetime": "2022-03-07 18:21:23", "elapsed": 0.0, "delta": 0.0}}
{"target": -2799.4528300000025, "params": {"spark.default.parallelism": 215.22772997867926, "spark.executor.cores": 3.2817901615029923, "spark.executor.instances": 6.857573573738841, "spark.executor.memory": 4.009155487372955, "spark.executor.memoryOverhead": 512.2153622320113, "spark.memory.fraction": 0.5684512807168226, "spark.memory.storageFraction": 0.7111968951407991, "spark.reducer.maxBlocksInFlightPerAddress": 1648555039.483582, "spark.reducer.maxSizeInFlight": 40.48891598651867, "spark.shuffle.file.buffer": 18.900373459885373}, "datetime": {"datetime": "2022-03-07 18:21:23", "elapsed": 0.031915, "delta": 0.031915}}
{"target": -2799.1022000000016, "params": {"spark.default.parallelism": 367.8507649543771, "spark.executor.cores": 1.213997416657705, "spark.executor.instances": 4.376853119816686, "spark.executor.memory": 5.674638437601342, "spark.executor.memoryOverhead": 610.2342302855996, "spark.memory.fraction": 0.7648584424097167, "spark.memory.storageFraction": 0.6236705645385547, "spark.reducer.maxBlocksInFlightPerAddress": 1880427359.442366, "spark.reducer.maxSizeInFlight": 26.567411418963182, "spark.shuffle.file.buffer": 30.40283135685036}, "datetime": {"datetime": "2022-03-07 18:21:23", "elapsed": 0.061835, "delta": 0.02992}}
